README.rst
setup.py
plotrique/__init__.py
plotrique/container.py
plotrique/plotting.py
plotrique/report.py
plotrique.egg-info/PKG-INFO
plotrique.egg-info/SOURCES.txt
plotrique.egg-info/dependency_links.txt
plotrique.egg-info/requires.txt
plotrique.egg-info/top_level.txt