Metadata-Version: 1.1
Name: plotrique
Version: 0.2.5-4a
Summary: plotrique - Convenience plotting tools
Home-page: https://github.com/drpoovilleorg/metrique
Author: Juraj Niznan
Author-email: jniznan@redhat.com
License: GPLv3
Download-URL: https://github.com/drpoovilleorg/metrique/archive/master.zip
Keywords: data,mining,information,mongo,etl,analysis,search,query
Platform: UNKNOWN
Classifier: Development Status :: 4 - Beta
Classifier: Intended Audience :: Science/Research
Classifier: License :: OSI Approved :: GNU General Public License v3 (GPLv3)
Classifier: Natural Language :: English
Classifier: Programming Language :: Python :: 2.6
Classifier: Programming Language :: Python :: 2.7
Classifier: Programming Language :: Python :: 2 :: Only
Classifier: Topic :: Database
Classifier: Topic :: Office/Business
Classifier: Topic :: Scientific/Engineering
Classifier: Topic :: Scientific/Engineering :: Artificial Intelligence
Classifier: Topic :: Scientific/Engineering :: Visualization
Classifier: Topic :: Utilities
Requires: pandas(==0.12)
Provides: plotrique
